{
  "materials": [
    {
      "id": "crt",
      "fragment_shader_path": "assets/materials/crt_fragment.glsl",
      "vertex_shader_path": "assets/materials/crt_vertex.glsl"
    }
  ],
  "textures": [
    {
      "id": "target_cursor",
      "path": "assets/textures/target_cursor.png"
    },
    {
      "id": "characters",
      "path": "assets/textures/neo_zero_characters.png"
    },
    {
      "id": "player",
      "path": "assets/textures/player.png"
    },
    {
      "id": "props",
      "path": "assets/textures/neo_zero_props.png"
    },
    {
      "id": "tiles",
      "path": "assets/textures/neo_zero_tiles.png"
    },
    {
      "id": "items",
      "path": "assets/textures/items.png"
    },
    {
      "id": "fireball",
      "path": "assets/textures/fireball.png"
    },
    {
      "id": "credits",
      "path": "assets/textures/credits.png"
    },
    {
      "id": "mission_marker",
      "path": "assets/textures/mission_marker.png"
    }
  ],
  "images": [
    {
      "id": "blank_image",
      "path": "assets/gui/blank_image.png"
    },
    {
      "id": "panel_01",
      "path": "assets/gui/macroquad_example_assets/window_background_2.png"
    },
    {
      "id": "panel_02",
      "path": "assets/gui/wenrexa/MainPanel03.png"
    },
    {
      "id": "editbox_01",
      "path": "assets/gui/macroquad_example_assets/editbox_background.png"
    },
    {
      "id": "btn_01",
      "path": "assets/gui/macroquad_example_assets/button_background_2.png"
    },
    {
      "id": "btn_01_hover",
      "path": "assets/gui/macroquad_example_assets/button_clicked_background_2.png"
    },
    {
      "id": "btn_01_click",
      "path": "assets/gui/macroquad_example_assets/button_hovered_background_2.png"
    },
    {
      "id": "btn_01_inactive",
      "path": "assets/gui/macroquad_example_assets/button_background_2_inactive.png"
    },
    {
      "id": "btn_02",
      "path": "assets/gui/wenrexa/Button11.png"
    },
    {
      "id": "btn_02_hover",
      "path": "assets/gui/wenrexa/Button12.png"
    },
    {
      "id": "btn_02_click",
      "path": "assets/gui/wenrexa/Button12.png"
    },
    {
      "id": "btn_03",
      "path": "assets/gui/wenrexa/Button04.png"
    },
    {
      "id": "btn_03_hover",
      "path": "assets/gui/wenrexa/Button02.png"
    },
    {
      "id": "btn_03_click",
      "path": "assets/gui/wenrexa/Button02.png"
    }
  ],
  "fonts": [
    {
      "id": "minimal_pixel_v2",
      "path": "assets/gui/fonts/MinimalPixel v2.ttf"
    },
    {
      "id": "high_tower_text_regular",
      "path": "assets/gui/fonts/HighTowerTextRegular.ttf"
    }
  ],
  "sound_effects": [
    {
      "id": "gunshot_01",
      "path": "assets/sound_effects/M4A1_Single.wav"
    },
    {
      "id": "gunshot_02",
      "path": "assets/sound_effects/9mm_Glock_17.wav"
    },
    {
      "id": "blaster_rifle_01",
      "path": "assets/sound_effects/Sci Fi Blaster 4.wav"
    },
    {
      "id": "blaster_pistol_01",
      "path": "assets/sound_effects/Sci Fi Pistol 4.wav"
    },
    {
      "id": "blaster_hit_01",
      "path": "assets/sound_effects/Sci Fi Blaster 9.wav"
    },
    {
      "id": "shock_melee_01",
      "path": "assets/sound_effects/Sci Fi Blaster 1.wav"
    },
    {
      "id": "shock_melee_hit_01",
      "path": "assets/sound_effects/Sci Fi Blaster 4.wav"
    }
  ],
  "music": []
}
